stochatreat/__about__.py
stochatreat/__init__.py
stochatreat/py.typed
stochatreat/stochatreat.py
stochatreat/utils.py
stochatreat-0.0.20.dist-info/METADATA
stochatreat-0.0.20.dist-info/WHEEL
stochatreat-0.0.20.dist-info/licenses/LICENSE
stochatreat-0.0.20.dist-info/RECORD
