Metadata-Version: 2.3
Name: stochatreat
Version: 0.0.20
Summary: Stratified random assignment using pandas
Project-URL: Documentation, https://github.com/manmartgarc/stochatreat/blob/main/README.md
Project-URL: Issues, https://github.com/manmartgarc/stochatreat/issues
Project-URL: Source, https://github.com/manmartgarc/stochatreat/
Author-email: Manuel Martinez <manmartgarc@gmail.com>
License-File: LICENSE
Keywords: block randomization,randomization,strata,stratified random assignment,stratified randomization
Classifier: Development Status :: 4 - Beta
Classifier: License :: OSI Approved :: MIT License
Classifier: Operating System :: OS Independent
Classifier: Programming Language :: Python
Classifier: Programming Language :: Python :: 3.9
Classifier: Programming Language :: Python :: 3.10
Classifier: Programming Language :: Python :: 3.11
Classifier: Programming Language :: Python :: 3.12
Classifier: Programming Language :: Python :: Implementation :: CPython
Classifier: Programming Language :: Python :: Implementation :: PyPy
Requires-Python: >=3.9
Requires-Dist: pandas>=2.2
